matrx_orm/__init__.py
matrx_orm/constants.py
matrx_orm/error_handling.py
matrx_orm/exceptions.py
matrx_orm/state.py
matrx_orm/structure.md
matrx_orm/adapters/__init__.py
matrx_orm/adapters/base_adapter.py
matrx_orm/adapters/postgresql.py
matrx_orm/client/__init__.py
matrx_orm/client/postgres_connection.py
matrx_orm/core/__init__.py
matrx_orm/core/async_db_manager.py
matrx_orm/core/base.py
matrx_orm/core/config.py
matrx_orm/core/expressions.py
matrx_orm/core/extended.py
matrx_orm/core/fields.py
matrx_orm/core/registry.py
matrx_orm/core/relations.py
matrx_orm/extended/__init__.py
matrx_orm/extended/app_error_handler.py
matrx_orm/middleware/__init__.py
matrx_orm/middleware/base.py
matrx_orm/operations/__init__.py
matrx_orm/operations/create.py
matrx_orm/operations/delete.py
matrx_orm/operations/read.py
matrx_orm/operations/update.py
matrx_orm/python_sql/__init__.py
matrx_orm/python_sql/db_objects.py
matrx_orm/python_sql/table_detailed_relationships.py
matrx_orm/python_sql/table_typescript_relationship.py
matrx_orm/query/__init__.py
matrx_orm/query/builder.py
matrx_orm/query/executor.py
matrx_orm/schema_builder/__init__.py
matrx_orm/schema_builder/generator.py
matrx_orm/schema_builder/schema_manager.py
matrx_orm/schema_builder/helpers/__init__.py
matrx_orm/schema_builder/helpers/configs.py
matrx_orm/schema_builder/helpers/git_checker.py
matrx_orm/schema_builder/helpers/manager_dto_creator.py
matrx_orm/schema_builder/helpers/manager_helpers.py
matrx_orm/schema_builder/helpers/manual_overrides.py
matrx_orm/schema_builder/individual_managers/__init__.py
matrx_orm/schema_builder/individual_managers/columns.py
matrx_orm/schema_builder/individual_managers/common.py
matrx_orm/schema_builder/individual_managers/relationships.py
matrx_orm/schema_builder/individual_managers/schema.py
matrx_orm/schema_builder/individual_managers/tables.py
matrx_orm/schema_builder/individual_managers/views.py
matrx_orm/schema_builder/parts_generators/__init__.py
matrx_orm-1.1.3.dist-info/METADATA
matrx_orm-1.1.3.dist-info/WHEEL
matrx_orm-1.1.3.dist-info/entry_points.txt
matrx_orm-1.1.3.dist-info/RECORD
