Metadata-Version: 2.4
Name: matrx-orm
Version: 1.1.3
Summary: Add your description here
Author-email: jatin.b.rx3@gmail.com
Requires-Python: >=3.10
Requires-Dist: asyncpg==0.30.0
Requires-Dist: gitpython>=3.1.44
Requires-Dist: matrx-utils>=1.0.2
Requires-Dist: psycopg2>=2.9.10
